mauztoolslib/__init__.py
mauztoolslib/detect_language.py
mauztoolslib/log.py
mauztoolslib/number.py
mauztoolslib/time.py
mauztoolslib/disklib/__init__.py
mauztoolslib/disklib/__main__.py
mauztoolslib/disklib/cli.py
mauztoolslib/disklib/diskusage.py
mauztoolslib/disklib/export.py
mauztoolslib/disklib/path.py
mauztoolslib/html/__init__.py
mauztoolslib/html/classes/document.py
mauztoolslib/html/classes/reader.py
mauztoolslib/html/classes/starter.py
mauztoolslib/html/classes/writer.py
mauztoolslib/html/functions/find_all.py
mauztoolslib/html/functions/from_tag_to_class.py
mauztoolslib/html/objects/heading.py
mauztoolslib/html/objects/image.py
mauztoolslib/html/objects/link.py
mauztoolslib/html/objects/paragraph.py
mauztoolslib/html/objects/script.py
mauztoolslib-0.1.7.dist-info/licenses/LICENSE
mauztoolslib-0.1.7.dist-info/METADATA
mauztoolslib-0.1.7.dist-info/WHEEL
mauztoolslib-0.1.7.dist-info/top_level.txt
mauztoolslib-0.1.7.dist-info/RECORD
