Metadata-Version: 2.4
Name: mauztoolslib
Version: 0.1.7
Summary: Tools for Python projects
Author-email: Fetelker <fetelkernils@gmail.com>
License-Expression: MIT
Requires-Python: >=3.10
License-File: LICENSE
Requires-Dist: pandas>=2.0.0
Requires-Dist: openpyxl>=3.1.0
Requires-Dist: pillow>=10.0.0
Provides-Extra: test
Dynamic: license-file
